[
{
    "id": "1",
    "product_name": "PHOTO GIFTS/SCRAPBOOKS",
    "paragraph_1": "Photo gifts are trending now with photos being customized and printed in various everyday products. We offer photo-based gifts like albums, mini albums, magnets, calendars, 3D albums, wall décor, boxes and many more. Our customizable scrapbooks give you the advantage of selecting the theme, color combination and even the sequence of photos, making it a treasured keepsake. Our scrapbooks can be made not only for occasions like weddings, anniversaries, birthdays but also marking a special day in your life. Blank albums can also be ordered to gift someone.",
    "paragraph_2": "The current trend is popup albums wherein the pages have various popup and interactive pages in the album to add a surprise and fun element!",
    "image_1": "/assets/img/products/photo-gift/1.jpg",
    "image_2": "/assets/img/products/photo-gift/2.JPG",
    "image_3": "/assets/img/products/photo-gift/3.JPG",
    "image_4": "/assets/img/products/photo-gift/4.JPG",
    "image_5": "/assets/img/products/photo-gift/5.jpg",
    "image_6": "/assets/img/products/photo-gift/6.JPG",
    "image_7": "/assets/img/products/photo-gift/7.jpg",
    "image_8": "/assets/img/products/photo-gift/8.jpg",
    "image_9": "/assets/img/products/photo-gift/9.jpg",
    "image_10": "/assets/img/products/photo-gift/10.jpg",
    "image_11": "/assets/img/products/photo-gift/11.jpg",
    "image_12": "/assets/img/products/photo-gift/12.jpg",
    "image_13": "/assets/img/products/photo-gift/13.jpg",
    "image_14": "/assets/img/products/photo-gift/14.jpg",
    "image_15": "/assets/img/products/photo-gift/15.jpg",
    "image_16": "/assets/img/products/photo-gift/16.jpg",
    "image_17": "/assets/img/products/photo-gift/17.JPG",
    "image_18": "/assets/img/products/photo-gift/18.JPG",
    "image_19": "/assets/img/products/photo-gift/19.jpg",
    "image_20": "/assets/img/products/photo-gift/20.jpg",
    "image_21": "/assets/img/products/photo-gift/21.jpg",
    "image_22": "/assets/img/products/photo-gift/22.jpg",
    "image_23": "/assets/img/products/photo-gift/23.jpg",
    "image_24": "/assets/img/products/photo-gift/24.jpg",
    "image_25": "/assets/img/products/photo-gift/25.jpg",
    "image_26":"/assets/img/products/photo-gift/26.jpg",
    "image_27":"/assets/img/products/photo-gift/27.jpg",
    "image_28":"/assets/img/products/photo-gift/28.jpg",
    "image_29":"",
    "image_30":"",
    "image_31":"",
    "image_32":"",
    "image_33":"",
    "image_34":"",
    "image_35":"",
    "image_36":"",
    "image_37":"",
    "image_38":"",
    "image_39":"",
    "image_40":"",
    "image_41":"",
    "image_42":"",
    "image_43":"",
    "image_44":"",
    "image_45":"",
    "image_46":"",
    "image_47":"",
    "image_48":"",
    "image_49":"",
    "image_50":"",
    "image_51":"",
    "image_52":"",
    "image_53":"",
    "image_54":""
},
{
    "id": "2",
    "product_name": "MDF ALBUMS",
    "paragraph_1": "Albums personalized with the names of the clients are the most sought-after products currently. MDF Albums are customized in the shape of the individual or a couple’s names. This can hold a large number of photos and messages and definitely proves to be an eye-catching gift.",
    "paragraph_2": "",
    "image_1": "/assets/img/products/mdf-albums/1.JPG",
    "image_2": "/assets/img/products/mdf-albums/2.JPG",
    "image_3": "/assets/img/products/mdf-albums/3.JPG",
    "image_4": "/assets/img/products/mdf-albums/4.jpg",
    "image_5": "/assets/img/products/mdf-albums/5.jpg",
    "image_6": "",
    "image_7": "",
    "image_8": "",
    "image_9": "",
    "image_10": "",
    "image_11": "",
    "image_12": "",
    "image_13": "",
    "image_14": "",
    "image_15": "",
    "image_16": "",
    "image_17": "",
    "image_18": "",
    "image_19": "",
    "image_20": "",
    "image_21": "",
    "image_22": "",
    "image_23": "",
    "image_24": "",
    "image_25": "",
    "image_26":"",
    "image_27":"",
    "image_28":"",
    "image_29":"",
    "image_30":"",
    "image_31":"",
    "image_32":"",
    "image_33":"",
    "image_34":"",
    "image_35":"",
    "image_36":"",
    "image_37":"",
    "image_38":"",
    "image_39":"",
    "image_40":"",
    "image_41":"",
    "image_42":"",
    "image_43":"",
    "image_44":"",
    "image_45":"",
    "image_46":"",
    "image_47":"",
    "image_48":"",
    "image_49":"",
    "image_50":"",
    "image_51":"",
    "image_52":"",
    "image_53":"",
    "image_54":""
},
{
    "id": "3",
    "product_name": "CARDS",
    "paragraph_1": "Bringing back the culture of sending your loved ones a personalized greeting card on their special day, in this otherwise social media dominated age, is our main aim in this genre. Our cards come in various forms like mini cards, two-fold cards, shaped cards and much more.",
    "paragraph_2": "",
    "image_1": "/assets/img/products/cards/1.JPG",
    "image_2": "/assets/img/products/cards/2.JPG",
    "image_3": "/assets/img/products/cards/3.jpg",
    "image_4": "/assets/img/products/cards/4.jpg",
    "image_5": "/assets/img/products/cards/5.jpg",
    "image_6": "/assets/img/products/cards/6.jpg",
    "image_7": "",
    "image_8": "",
    "image_9": "",
    "image_10": "",
    "image_11": "",
    "image_12": "",
    "image_13": "",
    "image_14": "",
    "image_15": "",
    "image_16": "",
    "image_17": "",
    "image_18": "",
    "image_19": "",
    "image_20": "",
    "image_21": "",
    "image_22": "",
    "image_23": "",
    "image_24": "",
    "image_25": "",
    "image_26":"",
    "image_27":"",
    "image_28":"",
    "image_29":"",
    "image_30":"",
    "image_31":"",
    "image_32":"",
    "image_33":"",
    "image_34":"",
    "image_35":"",
    "image_36":"",
    "image_37":"",
    "image_38":"",
    "image_39":"",
    "image_40":"",
    "image_41":"",
    "image_42":"",
    "image_43":"",
    "image_44":"",
    "image_45":"",
    "image_46":"",
    "image_47":"",
    "image_48":"",
    "image_49":"",
    "image_50":"",
    "image_51":"",
    "image_52":"",
    "image_53":"",
    "image_54":""
},
{
    "id": "4",
    "product_name": "3D CARDS",
    "paragraph_1": "3D Cards, like the name suggests, appears as a normal card, but quickly transforms into a 3D card that can become a stand-alone gift. This element of surprise is the key factor in making this the most favorite gifting option.",
    "paragraph_2": "",
    "image_1": "/assets/img/products/3d-cards/1.JPG",
    "image_2": "/assets/img/products/3d-cards/2.JPG",
    "image_3": "/assets/img/products/3d-cards/3.JPG",
    "image_4": "/assets/img/products/3d-cards/4.JPG",
    "image_5": "/assets/img/products/3d-cards/5.jpg",
    "image_6": "/assets/img/products/3d-cards/6.jpg",
    "image_7": "/assets/img/products/3d-cards/7.jpg",
    "image_8": "/assets/img/products/3d-cards/8.jpg",
    "image_9": "",
    "image_10": "",
    "image_11": "",
    "image_12": "",
    "image_13": "",
    "image_14": "",
    "image_15": "",
    "image_16": "",
    "image_17": "",
    "image_18": "",
    "image_19": "",
    "image_20": "",
    "image_21": "",
    "image_22": "",
    "image_23": "",
    "image_24": "",
    "image_25": "",
    "image_26":"",
    "image_27":"",
    "image_28":"",
    "image_29":"",
    "image_30":"",
    "image_31":"",
    "image_32":"",
    "image_33":"",
    "image_34":"",
    "image_35":"",
    "image_36":"",
    "image_37":"",
    "image_38":"",
    "image_39":"",
    "image_40":"",
    "image_41":"",
    "image_42":"",
    "image_43":"",
    "image_44":"",
    "image_45":"",
    "image_46":"",
    "image_47":"",
    "image_48":"",
    "image_49":"",
    "image_50":"",
    "image_51":"",
    "image_52":"",
    "image_53":"",
    "image_54":""
},
{
    "id": "5",
    "product_name": "ENVELOPES/INVITATIONS",
    "paragraph_1": "These products are specifically designed for weddings, engagements and other major events, but not restricted to just these occasions.",
    "paragraph_2": "",
    "image_1": "/assets/img/products/envelopes/1.JPG",
    "image_2": "/assets/img/products/envelopes/2.JPG",
    "image_3": "/assets/img/products/envelopes/3.jpg",
    "image_4": "/assets/img/products/envelopes/4.jpg",
    "image_5": "",
    "image_6": "",
    "image_7": "",
    "image_8": "",
    "image_9": "",
    "image_10": "",
    "image_11": "",
    "image_12": "",
    "image_13": "",
    "image_14": "",
    "image_15": "",
    "image_16": "",
    "image_17": "",
    "image_18": "",
    "image_19": "",
    "image_20": "",
    "image_21": "",
    "image_22": "",
    "image_23": "",
    "image_24": "",
    "image_25": "",
    "image_26":"",
    "image_27":"",
    "image_28":"",
    "image_29":"",
    "image_30":"",
    "image_31":"",
    "image_32":"",
    "image_33":"",
    "image_34":"",
    "image_35":"",
    "image_36":"",
    "image_37":"",
    "image_38":"",
    "image_39":"",
    "image_40":"",
    "image_41":"",
    "image_42":"",
    "image_43":"",
    "image_44":"",
    "image_45":"",
    "image_46":"",
    "image_47":"",
    "image_48":"",
    "image_49":"",
    "image_50":"",
    "image_51":"",
    "image_52":"",
    "image_53":"",
    "image_54":""
},
{
    "id": "6",
    "product_name": "FAVORS",
    "paragraph_1": "Favors or return gifts bring joy to people who share our special day with us and make our day extra joyous with their presence. Favors can be knick knacks, small gifts like magnets, door hangars or photo frames, boxes, goodies, candy or sweet bags, diyas and candles, post-it note holders, door hangars, paper weights and even cards. Favors are generally made to coincide with the theme, especially in case of weddings, birthdays or baby showers. They can also be customized for a specific get-together or meeting.",
    "paragraph_2": "",
    "image_1": "/assets/img/products/favors-gifts/1.png",
    "image_2": "/assets/img/products/favors-gifts/2.png",
    "image_3": "/assets/img/products/favors-gifts/3.jpg",
    "image_4": "/assets/img/products/favors-gifts/4.JPG",
    "image_5": "/assets/img/products/favors-gifts/5.JPG",
    "image_6": "/assets/img/products/favors-gifts/6.JPG",
    "image_7": "/assets/img/products/favors-gifts/7.JPG",
    "image_8": "/assets/img/products/favors-gifts/8.JPG",
    "image_9": "/assets/img/products/favors-gifts/9.JPG",
    "image_10": "/assets/img/products/favors-gifts/10.JPG",
    "image_11": "/assets/img/products/favors-gifts/11.JPG",
    "image_12": "/assets/img/products/favors-gifts/12.JPG",
    "image_13": "/assets/img/products/favors-gifts/13.JPG",
    "image_14": "/assets/img/products/favors-gifts/14.JPG",
    "image_15": "/assets/img/products/favors-gifts/15.JPG",
    "image_16": "/assets/img/products/favors-gifts/16.jpg",
    "image_17": "/assets/img/products/favors-gifts/17.jpg",
    "image_18": "/assets/img/products/favors-gifts/18.jpg",
    "image_19": "/assets/img/products/favors-gifts/19.JPG",
    "image_20": "/assets/img/products/favors-gifts/20.jpg",
    "image_21": "/assets/img/products/favors-gifts/21.jpg",
    "image_22": "/assets/img/products/favors-gifts/22.jpg",
    "image_23": "/assets/img/products/favors-gifts/23.jpg",
    "image_24": "/assets/img/products/favors-gifts/24.jpg",
    "image_25": "/assets/img/products/favors-gifts/25.jpg",
    "image_26":"/assets/img/products/favors-gifts/26.jpg",
    "image_27":"/assets/img/products/favors-gifts/27.jpg",
    "image_28":"/assets/img/products/favors-gifts/28.jpg",
    "image_29":"/assets/img/products/favors-gifts/29.jpg",
    "image_30":"/assets/img/products/favors-gifts/30.jpg",
    "image_31":"/assets/img/products/favors-gifts/31.jpg",
    "image_32":"/assets/img/products/favors-gifts/32.jpg",
    "image_33":"/assets/img/products/favors-gifts/33.jpg",
    "image_34":"/assets/img/products/favors-gifts/34.jpg",
    "image_35":"/assets/img/products/favors-gifts/35.jpg",
    "image_36":"/assets/img/products/favors-gifts/36.jpg",
    "image_37":"/assets/img/products/favors-gifts/37.jpg",
    "image_38":"/assets/img/products/favors-gifts/38.jpg",
    "image_39":"/assets/img/products/favors-gifts/39.jpg",
    "image_40":"/assets/img/products/favors-gifts/40.jpg",
    "image_41":"/assets/img/products/favors-gifts/41.jpg",
    "image_42":"/assets/img/products/favors-gifts/42.jpg",
    "image_43":"/assets/img/products/favors-gifts/43.jpg",
    "image_44":"/assets/img/products/favors-gifts/44.jpg",
    "image_45":"/assets/img/products/favors-gifts/45.jpg",
    "image_46":"/assets/img/products/favors-gifts/46.jpg",
    "image_47":"/assets/img/products/favors-gifts/47.jpg",
    "image_48":"/assets/img/products/favors-gifts/48.jpg",
    "image_49":"/assets/img/products/favors-gifts/49.jpg",
    "image_50":"/assets/img/products/favors-gifts/50.jpg",
    "image_51":"/assets/img/products/favors-gifts/51.jpg",
    "image_52":"/assets/img/products/favors-gifts/52.jpg",
    "image_53":"/assets/img/products/favors-gifts/53.jpg",
    "image_54":""
},
{
    "id": "7",
    "product_name": "WALL DÉCOR",
    "paragraph_1": "This category has a wide variety of products using MDF Wood, Cardstock, Paper, Canvas and so much more. The list of occasions these products serve as gifts include but not restricted to weddings, birthdays, anniversaries, house warming, baby showers. Name plates, canvas art, shadow boxes, photo art, clocks, dream catchers, photo frames, banners and decorations (birthdays, functions), paper flowers etc. are some of the products in this category.",
    "paragraph_2": "",
    "image_1": "/assets/img/products/wall-decor/1.JPG",
    "image_2": "/assets/img/products/wall-decor/2.JPG",
    "image_3": "/assets/img/products/wall-decor/3.jpg",
    "image_4": "/assets/img/products/wall-decor/4.jpg",
    "image_5": "/assets/img/products/wall-decor/5.jpg",
    "image_6": "/assets/img/products/wall-decor/6.jpg",
    "image_7": "/assets/img/products/wall-decor/7.jpg",
    "image_8": "/assets/img/products/wall-decor/8.jpg",
    "image_9": "/assets/img/products/wall-decor/9.jpg",
    "image_10": "/assets/img/products/wall-decor/10.jpg",
    "image_11": "/assets/img/products/wall-decor/11.jpg",
    "image_12": "/assets/img/products/wall-decor/12.jpg",
    "image_13": "/assets/img/products/wall-decor/13.jpg",
    "image_14": "/assets/img/products/wall-decor/14.jpg",
    "image_15": "/assets/img/products/wall-decor/15.jpg",
    "image_16": "/assets/img/products/wall-decor/16.jpg",
    "image_17": "/assets/img/products/wall-decor/17.jpg",
    "image_18": "/assets/img/products/wall-decor/18.jpg",
    "image_19": "/assets/img/products/wall-decor/19.jpg",
    "image_20": "/assets/img/products/wall-decor/20.jpg",
    "image_21": "/assets/img/products/wall-decor/21.jpg",
    "image_22": "/assets/img/products/wall-decor/22.jpg",
    "image_23": "/assets/img/products/wall-decor/23.jpg",
    "image_24": "/assets/img/products/wall-decor/24.jpg",
    "image_25": "/assets/img/products/wall-decor/25.jpg",
    "image_26":"/assets/img/products/wall-decor/26.jpg",
    "image_27":"/assets/img/products/wall-decor/27.jpg",
    "image_28":"",
    "image_29":"",
    "image_30":"",
    "image_31":"",
    "image_32":"",
    "image_33":"",
    "image_34":"",
    "image_35":"",
    "image_36":"",
    "image_37":"",
    "image_38":"",
    "image_39":"",
    "image_40":"",
    "image_41":"",
    "image_42":"",
    "image_43":"",
    "image_44":"",
    "image_45":"",
    "image_46":"",
    "image_47":"",
    "image_48":"",
    "image_49":"",
    "image_50":"",
    "image_51":"",
    "image_52":"",
    "image_53":"",
    "image_54":""
},
{
    "id": "8",
    "product_name": "DOODLE ART",
    "paragraph_1": "Doodle art and mandalas are not only therapeutic but also incorporated in various gifting options to add that uniqueness to the product. Magnets, Coasters, Canvas, Journals, Notebooks, Cards, Albums etc., the list is endless in this genre.",
    "paragraph_2": "",
    "image_1": "/assets/img/products/doodle/1.jpg",
    "image_2": "/assets/img/products/doodle/2.jpg",
    "image_3": "/assets/img/products/doodle/3.jpg",
    "image_4": "/assets/img/products/doodle/4.jpg",
    "image_5": "/assets/img/products/doodle/5.jpg",
    "image_6": "/assets/img/products/doodle/6.jpg",
    "image_7": "/assets/img/products/doodle/7.jpg",
    "image_8": "/assets/img/products/doodle/8.jpg",
    "image_9": "/assets/img/products/doodle/9.jpg",
    "image_10": "/assets/img/products/doodle/10.jpg",
    "image_11": "/assets/img/products/doodle/11.jpg",
    "image_12": "/assets/img/products/doodle/12.jpg",
    "image_13": "/assets/img/products/doodle/13.jpg",
    "image_14": "/assets/img/products/doodle/14.jpg",
    "image_15": "/assets/img/products/doodle/15.jpg",
    "image_16": "/assets/img/products/doodle/16.jpg",
    "image_17": "/assets/img/products/doodle/17.jpg",
    "image_18": "",
    "image_19": "",
    "image_20": "",
    "image_21": "",
    "image_22": "",
    "image_23": "",
    "image_24": "",
    "image_25": "",
    "image_26":"",
    "image_27":"",
    "image_28":"",
    "image_29":"",
    "image_30":"",
    "image_31":"",
    "image_32":"",
    "image_33":"",
    "image_34":"",
    "image_35":"",
    "image_36":"",
    "image_37":"",
    "image_38":"",
    "image_39":"",
    "image_40":"",
    "image_41":"",
    "image_42":"",
    "image_43":"",
    "image_44":"",
    "image_45":"",
    "image_46":"",
    "image_47":"",
    "image_48":"",
    "image_49":"",
    "image_50":"",
    "image_51":"",
    "image_52":"",
    "image_53":"",
    "image_54":""
},
{
    "id": "9",
    "product_name": "EXPLOSION BOXES",
    "paragraph_1": "Explosion boxes are a form of 3D cards which also serve the purpose of a gift box and a mini-album, making it quite versatile and budget-friendly. They can be made in different shapes, sizes and with multiple layers and / or multiple flap options, to suit any number of photos or messages. These products work for any event and are extremely flexible for alterations.",
    "paragraph_2": "",
    "image_1": "/assets/img/products/explosion/1.jpg",
    "image_2": "/assets/img/products/explosion/2.jpg",
    "image_3": "/assets/img/products/explosion/3.jpg",
    "image_4": "/assets/img/products/explosion/4.jpg",
    "image_5": "/assets/img/products/explosion/5.jpg",
    "image_6": "/assets/img/products/explosion/6.jpg",
    "image_7": "/assets/img/products/explosion/7.jpg",
    "image_8": "/assets/img/products/explosion/8.jpg",
    "image_9": "/assets/img/products/explosion/9.JPG",
    "image_10": "/assets/img/products/explosion/10.jpg",
    "image_11": "/assets/img/products/explosion/11.jpg",
    "image_12": "/assets/img/products/explosion/12.jpg",
    "image_13": "/assets/img/products/explosion/13.jpg",
    "image_14": "/assets/img/products/explosion/14.jpg",
    "image_15": "/assets/img/products/explosion/15.jpg",
    "image_16": "/assets/img/products/explosion/16.jpg",
    "image_17": "",
    "image_18": "",
    "image_19": "",
    "image_20": "",
    "image_21": "",
    "image_22": "",
    "image_23": "",
    "image_24": "",
    "image_25": "",
    "image_26":"",
    "image_27":"",
    "image_28":"",
    "image_29":"",
    "image_30":"",
    "image_31":"",
    "image_32":"",
    "image_33":"",
    "image_34":"",
    "image_35":"",
    "image_36":"",
    "image_37":"",
    "image_38":"",
    "image_39":"",
    "image_40":"",
    "image_41":"",
    "image_42":"",
    "image_43":"",
    "image_44":"",
    "image_45":"",
    "image_46":"",
    "image_47":"",
    "image_48":"",
    "image_49":"",
    "image_50":"",
    "image_51":"",
    "image_52":"",
    "image_53":"",
    "image_54":""
}
]